exceptbool/__init__.py
exceptbool/converted_except.py
exceptbool/except_converter.py
exceptbool/except_to_bool.py
exceptbool-1.2.1.dist-info/AUTHORS.rst
exceptbool-1.2.1.dist-info/LICENSE
exceptbool-1.2.1.dist-info/METADATA
exceptbool-1.2.1.dist-info/WHEEL
exceptbool-1.2.1.dist-info/top_level.txt
exceptbool-1.2.1.dist-info/RECORD
