Metadata-Version: 2.1
Name: exceptbool
Version: 1.2.1
Summary: Converts caught exception into bool value.
Home-page: https://github.com/konrad-kocik/exceptbool
Author: Konrad Kocik
Author-email: konrad.kocik@gmail.com
License: MIT license
Keywords: except exception catching bool boolean decorator context manager
Platform: UNKNOWN
Classifier: Development Status :: 5 - Production/Stable
Classifier: Intended Audience :: Developers
Classifier: License :: OSI Approved :: MIT License
Classifier: Natural Language :: English
Classifier: Programming Language :: Python :: 3
Classifier: Programming Language :: Python :: 3.5
Classifier: Programming Language :: Python :: 3.6
Classifier: Programming Language :: Python :: 3.7
